byakugan/__init__.py
byakugan/__main__.py
byakugan/cli.py
byakugan/commands/__init__.py
byakugan/commands/base.py
byakugan/commands/scan.py
byakugan_reporter-0.0.1.dist-info/DESCRIPTION.rst
byakugan_reporter-0.0.1.dist-info/METADATA
byakugan_reporter-0.0.1.dist-info/RECORD
byakugan_reporter-0.0.1.dist-info/WHEEL
byakugan_reporter-0.0.1.dist-info/entry_points.txt
byakugan_reporter-0.0.1.dist-info/metadata.json
byakugan_reporter-0.0.1.dist-info/top_level.txt
