Metadata-Version: 2.0
Name: byakugan-reporter
Version: 0.0.1
Summary: A program to scan all IP camera in a network.
Home-page: UNKNOWN
Author: suusojeat
Author-email: suusojeat@gmail.com
License: UNLICENSED
Keywords: cli
Platform: UNKNOWN
Requires-Dist: docopt
Provides-Extra: test
Requires-Dist: coverage; extra == 'test'
Requires-Dist: pytest; extra == 'test'
Requires-Dist: pytest-cov; extra == 'test'
